solar_forecast/__init__.py
solar_forecast/_df_combination.py
solar_forecast-0.1.2.dist-info/METADATA
solar_forecast-0.1.2.dist-info/WHEEL
solar_forecast-0.1.2.dist-info/RECORD
