Metadata-Version: 2.1
Name: solar-forecast
Version: 0.1.2
Summary: Forecast produccion energia solar fotovoltaica
Author: Julio Martinez del Pino
Author-email: juliomdp92@gmail.com
Requires-Python: >=3.9,<3.13
Classifier: Programming Language :: Python :: 3
Classifier: Programming Language :: Python :: 3.9
Classifier: Programming Language :: Python :: 3.10
Classifier: Programming Language :: Python :: 3.11
Classifier: Programming Language :: Python :: 3.12
Requires-Dist: astral (==3.2)
Requires-Dist: ephem (==4.1.*)
Requires-Dist: matplotlib (==3.8.*)
Requires-Dist: pandas (==2.1.*)
Requires-Dist: scikit-learn (==1.3.*)
